LICENSE
README.md
setup.cfg
setup.py
beehiiv/__init__.py
beehiiv/__version__.py
beehiiv/email_blasts.py
beehiiv/endpoint.py
beehiiv/posts.py
beehiiv/publications.py
beehiiv/referral_program.py
beehiiv/segments.py
beehiiv/subscriptions.py
beehiiv.egg-info/PKG-INFO
beehiiv.egg-info/SOURCES.txt
beehiiv.egg-info/dependency_links.txt
beehiiv.egg-info/requires.txt
beehiiv.egg-info/top_level.txt